Workbook

Sheet 📋 Sales Entry
B2: 🧾 DAILY SALES TRACKER | G2: Auto-Report System | H2: v1.0
B4: ⬇ Enter each sale below. Reports update automatically.
A6: # | B6: Date | C6: Item / Service | D6: Category | E6: Qty | F6: Unit Price | G6: Total Sale | H6: Discount | I6: Net Revenue
A8: 1 | B8: 46184 | C8: Panadol 500mg | D8: Medicine | E8: 3 | F8: 120 | G8: =IF(E8*F8=0,"",E8*F8) -> 360 | I8: =IF(G8="","",G8-IF(H8="",0,H8)) -> 360
A9: 2 | B9: 46184 | C9: Chicken Biryani | D9: Food & Beverage | E9: 2 | F9: 350 | G9: =IF(E9*F9=0,"",E9*F9) -> 700 | I9: =IF(G9="","",G9-IF(H9="",0,H9)) -> 700
A10: 3 | B10: 46184 | C10: Shampoo (Head&Shldr) | D10: Hair & Beauty | E10: 1 | F10: 650 | G10: =IF(E10*F10=0,"",E10*F10) -> 650 | H10: 50 | I10: =IF(G10="","",G10-IF(H10="",0,H10)) -> 600
A11: 4 | B11: 46184 | C11: USB-C Cable 1m | D11: Electronics | E11: 2 | F11: 280 | G11: =IF(E11*F11=0,"",E11*F11) -> 560 | I11: =IF(G11="","",G11-IF(H11="",0,H11)) -> 560
A12: 5 | B12: 46184 | C12: Men's Shirt | D12: Clothing | E12: 1 | F12: 1800 | G12: =IF(E12*F12=0,"",E12*F12) -> 1800 | H12: 100 | I12: =IF(G12="","",G12-IF(H12="",0,H12)) -> 1700
A13: 6 | B13: 46183 | C13: Cough Syrup | D13: Medicine | E13: 2 | F13: 180 | G13: =IF(E13*F13=0,"",E13*F13) -> 360 | I13: =IF(G13="","",G13-IF(H13="",0,H13)) -> 360
A14: 7 | B14: 46183 | C14: Naan + Karahi | D14: Food & Beverage | E14: 4 | F14: 450 | G14: =IF(E14*F14=0,"",E14*F14) -> 1800 | I14: =IF(G14="","",G14-IF(H14="",0,H14)) -> 1800
A15: 8 | B15: 46183 | C15: Hair Trim | D15: Hair & Beauty | E15: 2 | F15: 300 | G15: =IF(E15*F15=0,"",E15*F15) -> 600 | I15: =IF(G15="","",G15-IF(H15="",0,H15)) -> 600
A16: 9 | B16: 46182 | C16: Laptop Sleeve | D16: Electronics | E16: 1 | F16: 950 | G16: =IF(E16*F16=0,"",E16*F16) -> 950 | H16: 50 | I16: =IF(G16="","",G16-IF(H16="",0,H16)) -> 900
A17: 10 | B17: 46182 | C17: Jeans | D17: Clothing | E17: 1 | F17: 2500 | G17: =IF(E17*F17=0,"",E17*F17) -> 2500 | H17: 200 | I17: =IF(G17="","",G17-IF(H17="",0,H17)) -> 2300
A18: 11 | G18: =IF(E18*F18=0,"",E18*F18) | I18: =IF(G18="","",G18-IF(H18="",0,H18))
A19: 12 | G19: =IF(E19*F19=0,"",E19*F19) | I19: =IF(G19="","",G19-IF(H19="",0,H19))
A20: 13 | G20: =IF(E20*F20=0,"",E20*F20) | I20: =IF(G20="","",G20-IF(H20="",0,H20))
A21: 14 | G21: =IF(E21*F21=0,"",E21*F21) | I21: =IF(G21="","",G21-IF(H21="",0,H21))
A22: 15 | G22: =IF(E22*F22=0,"",E22*F22) | I22: =IF(G22="","",G22-IF(H22="",0,H22))
A23: 16 | G23: =IF(E23*F23=0,"",E23*F23) | I23: =IF(G23="","",G23-IF(H23="",0,H23))
A24: 17 | G24: =IF(E24*F24=0,"",E24*F24) | I24: =IF(G24="","",G24-IF(H24="",0,H24))
A25: 18 | G25: =IF(E25*F25=0,"",E25*F25) | I25: =IF(G25="","",G25-IF(H25="",0,H25))
A26: 19 | G26: =IF(E26*F26=0,"",E26*F26) | I26: =IF(G26="","",G26-IF(H26="",0,H26))
A27: 20 | G27: =IF(E27*F27=0,"",E27*F27) | I27: =IF(G27="","",G27-IF(H27="",0,H27))
A28: 21 | G28: =IF(E28*F28=0,"",E28*F28) | I28: =IF(G28="","",G28-IF(H28="",0,H28))
A29: 22 | G29: =IF(E29*F29=0,"",E29*F29) | I29: =IF(G29="","",G29-IF(H29="",0,H29))
... A107: 100 | G107: =IF(E107*F107=0,"",E107*F107) | I107: =IF(G107="","",G107-IF(H107="",0,H107))
B108: TOTALS | G108: =SUMIF(G8:G107,">0") -> 10280 | H108: =SUMIF(H8:H107,">0") -> 400 | I108: =SUMIF(I8:I107,">0") -> 9880

Sheet 📊 Daily Report
B2: 📊 DAILY SALES REPORT | E2: Select Date → | F2: 46184
B4: Change the date in F2 to view any day's report. Data pulls from Sales Entry tab.
B6: Total Transactions | C6: Gross Revenue | D6: Total Discounts | E6: Net Revenue | F6: Avg Sale Value
B7: =COUNTIFS('📋 Sales Entry'!B8:B107,F2,'📋 Sales Entry'!I8:I107,">0") -> 5 | C7: =SUMIF('📋 Sales Entry'!B8:B107,F2,'📋 Sales Entry'!G8:G107) -> 4070 | D7: =SUMIF('📋 Sales Entry'!B8:B107,F2,'📋 Sales Entry'!H8:H107) -> 150 | E7: =SUMIF('📋 Sales Entry'!B8:B107,F2,'📋 Sales Entry'!I8:I107) -> 3920 | F7: =IFERROR(SUMIF('📋 Sales Entry'!B8:B107,F2,'📋 Sales Entry'!I8:I107)/COUNTIFS('📋 Sales Entry'!B8:B107,F2,'📋 Sales Entry'!I8:I107,">0"),0) -> 784
B10: Category Breakdown
B11: Category | C11: Transactions | D11: Net Revenue | E11: % of Day
B12: Food & Beverage | C12: =COUNTIFS('📋 Sales Entry'!B8:B107,F2,'📋 Sales Entry'!D8:D107,B12,'📋 Sales Entry'!I8:I107,">0") -> 1 | D12: =SUMIFS('📋 Sales Entry'!I8:I107,'📋 Sales Entry'!B8:B107,F2,'📋 Sales Entry'!D8:D107,B12) -> 700 | E12: =IFERROR(D12/G7,0) -> 0
B13: Medicine | C13: =COUNTIFS('📋 Sales Entry'!B8:B107,F2,'📋 Sales Entry'!D8:D107,B13,'📋 Sales Entry'!I8:I107,">0") -> 1 | D13: =SUMIFS('📋 Sales Entry'!I8:I107,'📋 Sales Entry'!B8:B107,F2,'📋 Sales Entry'!D8:D107,B13) -> 360 | E13: =IFERROR(D13/G7,0) -> 0
B14: Clothing | C14: =COUNTIFS('📋 Sales Entry'!B8:B107,F2,'📋 Sales Entry'!D8:D107,B14,'📋 Sales Entry'!I8:I107,">0") -> 1 | D14: =SUMIFS('📋 Sales Entry'!I8:I107,'📋 Sales Entry'!B8:B107,F2,'📋 Sales Entry'!D8:D107,B14) -> 1700 | E14: =IFERROR(D14/G7,0) -> 0
B15: Electronics | C15: =COUNTIFS('📋 Sales Entry'!B8:B107,F2,'📋 Sales Entry'!D8:D107,B15,'📋 Sales Entry'!I8:I107,">0") -> 1 | D15: =SUMIFS('📋 Sales Entry'!I8:I107,'📋 Sales Entry'!B8:B107,F2,'📋 Sales Entry'!D8:D107,B15) -> 560 | E15: =IFERROR(D15/G7,0) -> 0
B16: Services | C16: =COUNTIFS('📋 Sales Entry'!B8:B107,F2,'📋 Sales Entry'!D8:D107,B16,'📋 Sales Entry'!I8:I107,">0") -> 0 | D16: =SUMIFS('📋 Sales Entry'!I8:I107,'📋 Sales Entry'!B8:B107,F2,'📋 Sales Entry'!D8:D107,B16) -> 0 | E16: =IFERROR(D16/G7,0) -> 0
B17: Hair & Beauty | C17: =COUNTIFS('📋 Sales Entry'!B8:B107,F2,'📋 Sales Entry'!D8:D107,B17,'📋 Sales Entry'!I8:I107,">0") -> 1 | D17: =SUMIFS('📋 Sales Entry'!I8:I107,'📋 Sales Entry'!B8:B107,F2,'📋 Sales Entry'!D8:D107,B17) -> 600 | E17: =IFERROR(D17/G7,0) -> 0
B18: Other | C18: =COUNTIFS('📋 Sales Entry'!B8:B107,F2,'📋 Sales Entry'!D8:D107,B18,'📋 Sales Entry'!I8:I107,">0") -> 0 | D18: =SUMIFS('📋 Sales Entry'!I8:I107,'📋 Sales Entry'!B8:B107,F2,'📋 Sales Entry'!D8:D107,B18) -> 0 | E18: =IFERROR(D18/G7,0) -> 0
B19: TOTAL | C19: =SUM(C12:C18) -> 5 | D19: =SUM(D12:D18) -> 3920 | E19: =SUM(E12:E18) -> 0
B21: Top 5 Items Today
B22: (Scroll Sales Entry tab and sort by Net Revenue for full detail)

Sheet 📈 Weekly Report
B2: 📈 WEEKLY SALES REPORT
B4: Week Start (Monday): | D4: 46181 | F4: Week End: | H4: =D4+6 -> 46187
B6: Day | C6: Date | D6: Transactions | E6: Gross Revenue | F6: Discounts | G6: Net Revenue | H6: vs. Prev Day
B7: Monday | C7: =$D$4+0 -> 46181 | D7: =COUNTIFS('📋 Sales Entry'!B8:B107,C7,'📋 Sales Entry'!I8:I107,">0") -> 0 | E7: =SUMIF('📋 Sales Entry'!B8:B107,C7,'📋 Sales Entry'!G8:G107) -> 0 | F7: =SUMIF('📋 Sales Entry'!B8:B107,C7,'📋 Sales Entry'!H8:H107) -> 0 | G7: =SUMIF('📋 Sales Entry'!B8:B107,C7,'📋 Sales Entry'!I8:I107) -> 0 | H7: —
B8: Tuesday | C8: =$D$4+1 -> 46182 | D8: =COUNTIFS('📋 Sales Entry'!B8:B107,C8,'📋 Sales Entry'!I8:I107,">0") -> 2 | E8: =SUMIF('📋 Sales Entry'!B8:B107,C8,'📋 Sales Entry'!G8:G107) -> 3450 | F8: =SUMIF('📋 Sales Entry'!B8:B107,C8,'📋 Sales Entry'!H8:H107) -> 250 | G8: =SUMIF('📋 Sales Entry'!B8:B107,C8,'📋 Sales Entry'!I8:I107) -> 3200 | H8: =IFERROR((G8-G7)/G7,0) -> 0
B9: Wednesday | C9: =$D$4+2 -> 46183 | D9: =COUNTIFS('📋 Sales Entry'!B8:B107,C9,'📋 Sales Entry'!I8:I107,">0") -> 3 | E9: =SUMIF('📋 Sales Entry'!B8:B107,C9,'📋 Sales Entry'!G8:G107) -> 2760 | F9: =SUMIF('📋 Sales Entry'!B8:B107,C9,'📋 Sales Entry'!H8:H107) -> 0 | G9: =SUMIF('📋 Sales Entry'!B8:B107,C9,'📋 Sales Entry'!I8:I107) -> 2760 | H9: =IFERROR((G9-G8)/G8,0) -> -0.1375
B10: Thursday | C10: =$D$4+3 -> 46184 | D10: =COUNTIFS('📋 Sales Entry'!B8:B107,C10,'📋 Sales Entry'!I8:I107,">0") -> 5 | E10: =SUMIF('📋 Sales Entry'!B8:B107,C10,'📋 Sales Entry'!G8:G107) -> 4070 | F10: =SUMIF('📋 Sales Entry'!B8:B107,C10,'📋 Sales Entry'!H8:H107) -> 150 | G10: =SUMIF('📋 Sales Entry'!B8:B107,C10,'📋 Sales Entry'!I8:I107) -> 3920 | H10: =IFERROR((G10-G9)/G9,0) -> 0.42028986
B11: Friday | C11: =$D$4+4 -> 46185 | D11: =COUNTIFS('📋 Sales Entry'!B8:B107,C11,'📋 Sales Entry'!I8:I107,">0") -> 0 | E11: =SUMIF('📋 Sales Entry'!B8:B107,C11,'📋 Sales Entry'!G8:G107) -> 0 | F11: =SUMIF('📋 Sales Entry'!B8:B107,C11,'📋 Sales Entry'!H8:H107) -> 0 | G11: =SUMIF('📋 Sales Entry'!B8:B107,C11,'📋 Sales Entry'!I8:I107) -> 0 | H11: =IFERROR((G11-G10)/G10,0) -> -1
B12: Saturday | C12: =$D$4+5 -> 46186 | D12: =COUNTIFS('📋 Sales Entry'!B8:B107,C12,'📋 Sales Entry'!I8:I107,">0") -> 0 | E12: =SUMIF('📋 Sales Entry'!B8:B107,C12,'📋 Sales Entry'!G8:G107) -> 0 | F12: =SUMIF('📋 Sales Entry'!B8:B107,C12,'📋 Sales Entry'!H8:H107) -> 0 | G12: =SUMIF('📋 Sales Entry'!B8:B107,C12,'📋 Sales Entry'!I8:I107) -> 0 | H12: =IFERROR((G12-G11)/G11,0) -> 0
B13: Sunday | C13: =$D$4+6 -> 46187 | D13: =COUNTIFS('📋 Sales Entry'!B8:B107,C13,'📋 Sales Entry'!I8:I107,">0") -> 0 | E13: =SUMIF('📋 Sales Entry'!B8:B107,C13,'📋 Sales Entry'!G8:G107) -> 0 | F13: =SUMIF('📋 Sales Entry'!B8:B107,C13,'📋 Sales Entry'!H8:H107) -> 0 | G13: =SUMIF('📋 Sales Entry'!B8:B107,C13,'📋 Sales Entry'!I8:I107) -> 0 | H13: =IFERROR((G13-G12)/G12,0) -> 0
B14: WEEK TOTAL | D14: =SUM(D7:D13) -> 10 | E14: =SUM(E7:E13) -> 10280 | F14: =SUM(F7:F13) -> 400 | G14: =SUM(G7:G13) -> 9880
B16: Weekly Summary
B17: Best Day | D17: =INDEX(B7:B13,MATCH(MAX(G7:G13),G7:G13,0)) -> Thursday
B18: Best Revenue | D18: =MAX(G7:G13) -> 3920
B19: Worst Day | D19: =IFERROR(INDEX(B7:B13,MATCH(MAX(G7:G13),G7:G13,0)),"—") -> Thursday
B20: Daily Avg | D20: =IFERROR(G14/COUNTIF(G7:G13,">0"),0) -> 3293.3333

Sheet 📅 Monthly Report
B2: 📅 MONTHLY SALES REPORT
B4: Select Month (1–12): | D4: 6 | E4: Year: | F4: 2026
B6: Category Performance
B7: Category | C7: Transactions | D7: Net Revenue | E7: Avg Sale | F7: % Share
B8: Food & Beverage | C8: =SUMPRODUCT((MONTH('📋 Sales Entry'!B8:B107)=$D$4)*(YEAR('📋 Sales Entry'!B8:B107)=$F$4)*('📋 Sales Entry'!D8:D107=B8)*('📋 Sales Entry'!I8:I107>0)) -> 2 | D8: =SUMPRODUCT((MONTH('📋 Sales Entry'!B8:B107)=$D$4)*(YEAR('📋 Sales Entry'!B8:B107)=$F$4)*('📋 Sales Entry'!D8:D107=B8)*IFERROR('📋 Sales Entry'!I8:I107*1,0)) -> 2500 | E8: =IFERROR(D8/C8,0) -> 1250 | F8: =IFERROR(D8/G16,0) -> 0
B9: Medicine | C9: =SUMPRODUCT((MONTH('📋 Sales Entry'!B8:B107)=$D$4)*(YEAR('📋 Sales Entry'!B8:B107)=$F$4)*('📋 Sales Entry'!D8:D107=B9)*('📋 Sales Entry'!I8:I107>0)) -> 2 | D9: =SUMPRODUCT((MONTH('📋 Sales Entry'!B8:B107)=$D$4)*(YEAR('📋 Sales Entry'!B8:B107)=$F$4)*('📋 Sales Entry'!D8:D107=B9)*IFERROR('📋 Sales Entry'!I8:I107*1,0)) -> 720 | E9: =IFERROR(D9/C9,0) -> 360 | F9: =IFERROR(D9/G16,0) -> 0
B10: Clothing | C10: =SUMPRODUCT((MONTH('📋 Sales Entry'!B8:B107)=$D$4)*(YEAR('📋 Sales Entry'!B8:B107)=$F$4)*('📋 Sales Entry'!D8:D107=B10)*('📋 Sales Entry'!I8:I107>0)) -> 2 | D10: =SUMPRODUCT((MONTH('📋 Sales Entry'!B8:B107)=$D$4)*(YEAR('📋 Sales Entry'!B8:B107)=$F$4)*('📋 Sales Entry'!D8:D107=B10)*IFERROR('📋 Sales Entry'!I8:I107*1,0)) -> 4000 | E10: =IFERROR(D10/C10,0) -> 2000 | F10: =IFERROR(D10/G16,0) -> 0
B11: Electronics | C11: =SUMPRODUCT((MONTH('📋 Sales Entry'!B8:B107)=$D$4)*(YEAR('📋 Sales Entry'!B8:B107)=$F$4)*('📋 Sales Entry'!D8:D107=B11)*('📋 Sales Entry'!I8:I107>0)) -> 2 | D11: =SUMPRODUCT((MONTH('📋 Sales Entry'!B8:B107)=$D$4)*(YEAR('📋 Sales Entry'!B8:B107)=$F$4)*('📋 Sales Entry'!D8:D107=B11)*IFERROR('📋 Sales Entry'!I8:I107*1,0)) -> 1460 | E11: =IFERROR(D11/C11,0) -> 730 | F11: =IFERROR(D11/G16,0) -> 0
B12: Services | C12: =SUMPRODUCT((MONTH('📋 Sales Entry'!B8:B107)=$D$4)*(YEAR('📋 Sales Entry'!B8:B107)=$F$4)*('📋 Sales Entry'!D8:D107=B12)*('📋 Sales Entry'!I8:I107>0)) -> 0 | D12: =SUMPRODUCT((MONTH('📋 Sales Entry'!B8:B107)=$D$4)*(YEAR('📋 Sales Entry'!B8:B107)=$F$4)*('📋 Sales Entry'!D8:D107=B12)*IFERROR('📋 Sales Entry'!I8:I107*1,0)) -> 0 | E12: =IFERROR(D12/C12,0) -> 0 | F12: =IFERROR(D12/G16,0) -> 0
B13: Hair & Beauty | C13: =SUMPRODUCT((MONTH('📋 Sales Entry'!B8:B107)=$D$4)*(YEAR('📋 Sales Entry'!B8:B107)=$F$4)*('📋 Sales Entry'!D8:D107=B13)*('📋 Sales Entry'!I8:I107>0)) -> 2 | D13: =SUMPRODUCT((MONTH('📋 Sales Entry'!B8:B107)=$D$4)*(YEAR('📋 Sales Entry'!B8:B107)=$F$4)*('📋 Sales Entry'!D8:D107=B13)*IFERROR('📋 Sales Entry'!I8:I107*1,0)) -> 1200 | E13: =IFERROR(D13/C13,0) -> 600 | F13: =IFERROR(D13/G16,0) -> 0
B14: Other | C14: =SUMPRODUCT((MONTH('📋 Sales Entry'!B8:B107)=$D$4)*(YEAR('📋 Sales Entry'!B8:B107)=$F$4)*('📋 Sales Entry'!D8:D107=B14)*('📋 Sales Entry'!I8:I107>0)) -> 0 | D14: =SUMPRODUCT((MONTH('📋 Sales Entry'!B8:B107)=$D$4)*(YEAR('📋 Sales Entry'!B8:B107)=$F$4)*('📋 Sales Entry'!D8:D107=B14)*IFERROR('📋 Sales Entry'!I8:I107*1,0)) -> 0 | E14: =IFERROR(D14/C14,0) -> 0 | F14: =IFERROR(D14/G16,0) -> 0
B15: MONTH TOTAL | C15: =SUM(C8:C14) -> 10 | D15: =SUM(D8:D14) -> 9880 | F15: 100.0%
B17: Monthly Summary
B18: Total Revenue | D18: =D15 -> 9880
B19: Total Transactions | D19: =C15 -> 10
B20: Average Daily Rev | D20: =IFERROR(D15/SUMPRODUCT((MONTH('📋 Sales Entry'!B8:B107)=$D$4)*(YEAR('📋 Sales Entry'!B8:B107)=$F$4)*(IFERROR('📋 Sales Entry'!I8:I107*1,0)>0)),0) -> 988
B21: Top Category | D21: =IFERROR(INDEX(B8:B14,MATCH(MAX(D8:D14),D8:D14,0)),"—") -> Clothing

Sheet ℹ️ How to Use
B2: ℹ️ HOW TO USE THIS SYSTEM
B6: Step 1: Open the 📋 Sales Entry tab | C6: Enter every sale: Date, Item Name, Category, Qty, Unit Price. Discount is optional.
B7: Step 2: Total Sale is auto-calculated | C7: Column G (Total Sale) = Qty × Unit Price automatically. You don't type anything.
B8: Step 3: Net Revenue is auto-calculated | C8: Column I (Net Revenue) = Total Sale − Discount. Updates instantly.
B9: Step 4: View Daily Report | C9: Go to 📊 Daily Report tab. Change the date in cell F2 to see any day's summary.
B10: Step 5: View Weekly Report | C10: Go to 📈 Weekly Report tab. Change the Monday date in D4 to pick your week.
B11: Step 6: View Monthly Report | C11: Go to 📅 Monthly Report tab. Change month (D4) and year (F4) to see the month.
B12: Tip: Category dropdown | C12: In Sales Entry column D, pick from the dropdown: Food, Medicine, Clothing, etc.
B13: Tip: Add more rows if needed | C13: The entry table supports 100 rows. Copy-paste row formulas down for more.
B14: Tip: Backup regularly | C14: Save a copy each month with the month name, e.g. Sales_June_2026.xlsx
